snaken-0.0.1.dist-info/METADATA
snaken-0.0.1.dist-info/WHEEL
snaken-0.0.1.dist-info/licenses/LICENSE
snaken/__init__.py
snaken-0.0.1.dist-info/RECORD
